langeroodi_test/__init__.py
langeroodi_test/print_line.py
langeroodi_test-0.1.dist-info/METADATA
langeroodi_test-0.1.dist-info/WHEEL
langeroodi_test-0.1.dist-info/top_level.txt
langeroodi_test-0.1.dist-info/RECORD
