Metadata-Version: 2.1
Name: langeroodi_test
Version: 0.1
Summary: PyPi test package!
Author: Danial Langeroodi
Author-email: dlangaroudi@gmail.com
Classifier: Programming Language :: Python :: 3
Classifier: Operating System :: OS Independent
Requires-Python: >=3.6
